myfunctions_thejondaw/__init__.py
myfunctions_thejondaw/math.py
myfunctions_thejondaw-0.0.12.dist-info/METADATA
myfunctions_thejondaw-0.0.12.dist-info/WHEEL
myfunctions_thejondaw-0.0.12.dist-info/top_level.txt
myfunctions_thejondaw-0.0.12.dist-info/RECORD
