Metadata-Version: 2.1
Name: myfunctions-thejondaw
Version: 0.0.12
Summary: A description of your package
Home-page: https://github.com/thejondaw
Author: Jon Daw
Author-email: mrjondaw@gmail.com
License: MIT
Platform: UNKNOWN
Classifier: Programming Language :: Python :: 3
Classifier: License :: OSI Approved :: MIT License
Classifier: Operating System :: OS Independent
Requires-Python: >=3.6
Requires-Dist: os
